autocommit.py
kommiter-0.0.1.dist-info/LICENSE
kommiter-0.0.1.dist-info/METADATA
kommiter-0.0.1.dist-info/WHEEL
kommiter-0.0.1.dist-info/entry_points.txt
kommiter-0.0.1.dist-info/top_level.txt
kommiter-0.0.1.dist-info/zip-safe
kommiter-0.0.1.dist-info/RECORD
